README.md
setup.py
mysql_toolbox.egg-info/PKG-INFO
mysql_toolbox.egg-info/SOURCES.txt
mysql_toolbox.egg-info/dependency_links.txt
mysql_toolbox.egg-info/entry_points.txt
mysql_toolbox.egg-info/requires.txt
mysql_toolbox.egg-info/top_level.txt
toolbox/__init__.py
toolbox/__main__.py
toolbox/mysql_replication_display.py
toolbox/mysqlx.py
toolbox/xml_formatter.py